setup.py
exchars/__init__.py
exchars/exchars.py
exchars-0.0.3.dist-info/LICENSE
exchars-0.0.3.dist-info/METADATA
exchars-0.0.3.dist-info/WHEEL
exchars-0.0.3.dist-info/top_level.txt
exchars-0.0.3.dist-info/RECORD
