Metadata-Version: 2.1
Name: exchars
Version: 0.0.3
Summary: I got tired of downloading the whole PwnTools suite when I only use the cyclic functionality. This is meant to just generate random chars, find the position of the chars, and also generate bad char blobs for exploitation purposes.
Author-email: Brian M <DONOTEMAILME@mail.com>
Project-URL: Homepage, https://github.com/markersmake/exchars
Project-URL: Issues, https://github.com/markersmake/exchars/issues
Classifier: Programming Language :: Python :: 3
Classifier: License :: OSI Approved :: MIT License
Classifier: Operating System :: OS Independent
Requires-Python: >=3.6
License-File: LICENSE
